Metadata-Version: 2.1
Name: soda-core-teradata
Version: 3.5.6
License-File: LICENSE
Requires-Dist: soda-core==3.5.6
Requires-Dist: teradatasql>=17.10.0.0
